pydirecte/__init__.py
pydirecte/index.py
pydirecte-1.0.3.dist-info/licenses/LICENSE
pydirecte-1.0.3.dist-info/METADATA
pydirecte-1.0.3.dist-info/WHEEL
pydirecte-1.0.3.dist-info/top_level.txt
pydirecte-1.0.3.dist-info/RECORD
