Metadata-Version: 2.4
Name: pydirecte
Version: 1.0.3
Summary: A Python API wrapper for EcoleDirecte
Author: kikkopy
License: GPL-3.0-or-later
Project-URL: Homepage, https://github.com/kikkopy/pydirecte
Project-URL: Documentation, https://github.com/kikkopy/pydirecte#readme
Project-URL: Repository, https://github.com/kikkopy/pydirecte
Project-URL: Bug Tracker, https://github.com/kikkopy/pydirecte/issues
Keywords: ecoledirecte,api,wrapper,school,education
Classifier: Development Status :: 4 - Beta
Classifier: Intended Audience :: Developers
Classifier: Topic :: Software Development :: Libraries :: Python Modules
Classifier: License :: OSI Approved :: GNU General Public License v3 or later (GPLv3+)
Classifier: Programming Language :: Python :: 3
Classifier: Programming Language :: Python :: 3.8
Classifier: Programming Language :: Python :: 3.9
Classifier: Programming Language :: Python :: 3.10
Classifier: Programming Language :: Python :: 3.11
Classifier: Programming Language :: Python :: 3.12
Requires-Python: >=3.8
License-File: LICENSE
Requires-Dist: requests>=2.31.0
Dynamic: license-file
